LICENSE
MANIFEST.in
README.md
package.json
setup.py
dash_grocery/Barcode.py
dash_grocery/Clock.py
dash_grocery/LazyLoad.py
dash_grocery/Masonry.py
dash_grocery/MouseParticles.py
dash_grocery/ParticlesBg.py
dash_grocery/PowerModeInput.py
dash_grocery/QRCodeCanvas.py
dash_grocery/QRCodeSVG.py
dash_grocery/Snake.py
dash_grocery/Stars.py
dash_grocery/Textfit.py
dash_grocery/Weather.py
dash_grocery/__init__.py
dash_grocery/_imports_.py
dash_grocery/dash_grocery.min.js
dash_grocery/dash_grocery.min.js.map
dash_grocery/metadata.json
dash_grocery/package-info.json
dash_grocery.egg-info/PKG-INFO
dash_grocery.egg-info/SOURCES.txt
dash_grocery.egg-info/dependency_links.txt
dash_grocery.egg-info/top_level.txt
tests/test_components.py