Metadata-Version: 2.1
Name: dash_grocery
Version: 0.0.7
Summary: Project Description
Author: IcToxi <example@email.com>
License: MIT
Classifier: Framework :: Dash
License-File: LICENSE
